nlp_cleaner/nlp_cleaner.py
nlp_cleaner/string_formatter.py
nlp_cleaner-0.0.2.dist-info/LICENSE
nlp_cleaner-0.0.2.dist-info/METADATA
nlp_cleaner-0.0.2.dist-info/WHEEL
nlp_cleaner-0.0.2.dist-info/top_level.txt
nlp_cleaner-0.0.2.dist-info/RECORD
